sqez/__init__.py
sqez/py.typed
sqez-1.0.0.dist-info/METADATA
sqez-1.0.0.dist-info/WHEEL
sqez-1.0.0.dist-info/licenses/LICENSE
sqez-1.0.0.dist-info/RECORD
