Metadata-Version: 2.4
Name: sqez
Version: 1.0.0
Summary: Thin thread-safe wrapper around sqlite3
Project-URL: Homepage, https://github.com/Calvin-L/sqez
Project-URL: Issues, https://github.com/Calvin-L/sqez/issues
Author-email: Calvin Loncaric <c.a.loncaric@gmail.com>
License-Expression: MIT
License-File: LICENSE
Classifier: License :: OSI Approved :: MIT License
Classifier: Operating System :: OS Independent
Classifier: Programming Language :: Python :: 3
Requires-Python: >=3.11
